llama_web_scraper/__init__.py
llama_web_scraper/config.py
llama_web_scraper/core.py
llama_web_scraper/main.py
llama_web_scraper/ai/__init__.py
llama_web_scraper/ai/llm_processor.py
llama_web_scraper/cli/__init__.py
llama_web_scraper/cli/commands.py
llama_web_scraper/models/__init__.py
llama_web_scraper/models/data_models.py
llama_web_scraper/scraper/__init__.py
llama_web_scraper/scraper/crawler.py
llama_web_scraper/scraper/duckduckgo_search.py
llama_web_scraper/scraper/extractor.py
llama_web_scraper/utils/__init__.py
llama_web_scraper/utils/db_utils.py
llama_web_scraper/utils/logging_config.py
llama_web_scraper/utils/nlp_utils.py
llama_web_scraper/utils/schema_validator.py
llama_web_scraper-0.1.0.dist-info/METADATA
llama_web_scraper-0.1.0.dist-info/WHEEL
llama_web_scraper-0.1.0.dist-info/licenses/LICENSE
llama_web_scraper-0.1.0.dist-info/RECORD
