Metadata-Version: 2.4
Name: llama-web-scraper
Version: 0.1.0
Summary: Web scraping tool potentially using Llama models.
Project-URL: Homepage, https://github.com/yourusername/llama-web-scraper
Project-URL: Bug Tracker, https://github.com/yourusername/llama-web-scraper/issues
Author-email: Your Name <your.email@example.com>
License-File: LICENSE
Classifier: Development Status :: 3 - Alpha
Classifier: Intended Audience :: Developers
Classifier: Programming Language :: Python :: 3
Classifier: Programming Language :: Python :: 3.8
Classifier: Programming Language :: Python :: 3.9
Classifier: Programming Language :: Python :: 3.10
Classifier: Programming Language :: Python :: 3.11
Classifier: Topic :: Internet :: WWW/HTTP
Classifier: Topic :: Software Development :: Libraries :: Python Modules
Requires-Python: >=3.8
Requires-Dist: aiohttp
Requires-Dist: beautifulsoup4
Requires-Dist: datasette
Requires-Dist: duckduckgo-search
Requires-Dist: html2text-rs
Requires-Dist: jsonschema-rs
Requires-Dist: loguru
Requires-Dist: nltk
Requires-Dist: openai
Requires-Dist: pdfkit
Requires-Dist: pillow
Requires-Dist: playwright
Requires-Dist: proxy-inspector
Requires-Dist: pydantic
Requires-Dist: pypdf2
Requires-Dist: pytesseract
Requires-Dist: python-dotenv
Requires-Dist: requests
Requires-Dist: rich
Requires-Dist: sqlite-utils
Requires-Dist: typer[all]
Provides-Extra: all
Requires-Dist: black; extra == 'all'
Requires-Dist: isort; extra == 'all'
Requires-Dist: mypy; extra == 'all'
Requires-Dist: pre-commit; extra == 'all'
Requires-Dist: pytest; extra == 'all'
Requires-Dist: pytest-cov; extra == 'all'
Requires-Dist: pytest-mock; extra == 'all'
Requires-Dist: ruff; extra == 'all'
Provides-Extra: dev
Requires-Dist: black; extra == 'dev'
Requires-Dist: isort; extra == 'dev'
Requires-Dist: mypy; extra == 'dev'
Requires-Dist: pre-commit; extra == 'dev'
Requires-Dist: pytest; extra == 'dev'
Requires-Dist: pytest-cov; extra == 'dev'
Requires-Dist: pytest-mock; extra == 'dev'
Requires-Dist: ruff; extra == 'dev'
